smart_terminal/__init__.py
smart_terminal/cli_tool.py
smart_terminal/config.json
smart_terminal-0.0.2.dist-info/METADATA
smart_terminal-0.0.2.dist-info/WHEEL
smart_terminal-0.0.2.dist-info/entry_points.txt
smart_terminal-0.0.2.dist-info/top_level.txt
smart_terminal-0.0.2.dist-info/RECORD
